gmpykit/__init__.py
gmpykit/cache.py
gmpykit/charts.py
gmpykit/colors.py
gmpykit/dates.py
gmpykit/eta.py
gmpykit/execution.py
gmpykit/file.py
gmpykit/llm.py
gmpykit/math.py
gmpykit/timestamps.py
gmpykit/xml.py
gmpykit/dataframes/__init__.py
gmpykit/dataframes/analyze.py
gmpykit/dataframes/in_out.py
gmpykit/ipython/__init__.py
gmpykit/ipython/cache.py
gmpykit/ipython/dataframe.py
gmpykit/ipython/run.py
gmpykit/strings/__init__.py
gmpykit/strings/comparisons.py
gmpykit/strings/editing.py
gmpykit/strings/format.py
gmpykit/strings/numbers.py
gmpykit-0.4.11.dist-info/LICENSE
gmpykit-0.4.11.dist-info/METADATA
gmpykit-0.4.11.dist-info/WHEEL
gmpykit-0.4.11.dist-info/top_level.txt
gmpykit-0.4.11.dist-info/RECORD
