Metadata-Version: 2.1
Name: gmpykit
Version: 0.4.11
Summary: Package with various python tools
Author: Gaétan Muck
Author-email: gaetan.muck@gmail.com
Keywords: python,toolkit,utilities,utils,tools
License-File: LICENSE
Requires-Dist: pandas ==2.0.3
Requires-Dist: numpy ==1.26.2
Requires-Dist: pyyaml ==6.0.1
Requires-Dist: jdcal ==1.4.1
Requires-Dist: lxml ==4.9.3
Requires-Dist: plotly ==5.18.0
